across/__init__.py
across/abis/bridge_pool_abi.json
across/abis/rate_model_store_abi.json
across/api.py
across/block_finder.py
across/clients.py
across/constants.py
across/exceptions.py
across/fee_calculator.py
across/lp_fee_calculator.py
across/rate_model.py
across/utils.py
across_py-0.1.0.dist-info/LICENSE
across_py-0.1.0.dist-info/WHEEL
across_py-0.1.0.dist-info/METADATA
across_py-0.1.0.dist-info/RECORD
