Metadata-Version: 2.1
Name: across-py
Version: 0.1.0
Summary: across sdk in python
Home-page: https://github.com/qiwihui/across-py
License: MIT
Keywords: across,UMA,layer2,bridge
Author: qiwihui
Author-email: qwh005007@gmail.com
Maintainer: qiwihui
Maintainer-email: qwh005007@gmail.com
Requires-Python: >=3.8,<4.0
Classifier: License :: OSI Approved :: MIT License
Classifier: Operating System :: OS Independent
Classifier: Programming Language :: Python :: 3
Classifier: Programming Language :: Python :: 3.10
Classifier: Programming Language :: Python :: 3.8
Classifier: Programming Language :: Python :: 3.9
Requires-Dist: requests (>=2.26.0,<3.0.0)
Requires-Dist: web3 (>=5.28.0,<6.0.0)
Project-URL: Repository, https://github.com/qiwihui/across-py
